linque/__init__.py
linque/iters.py
linque/linque.py
unittests/__init__.py
unittests/test_iters.py
unittests/test_linq.py
linque-5.0.0.dist-info/LICENSE
linque-5.0.0.dist-info/METADATA
linque-5.0.0.dist-info/WHEEL
linque-5.0.0.dist-info/top_level.txt
linque-5.0.0.dist-info/RECORD
