Metadata-Version: 2.1
Name: linque
Version: 5.0.0
Summary: Linear Query - Python replica of popular .NET LINQ utilities.
Home-page: https://github.com/xxao/linque
Author: Martin Strohalm
Author-email: 
License: MIT
Classifier: Development Status :: 5 - Production/Stable
Classifier: Programming Language :: Python :: 3 :: Only
Classifier: Operating System :: OS Independent
Classifier: Topic :: Utilities
License-File: LICENSE
